{
  "bg": {
    "base": {
      "$type": "color",
      "$value": "{color.graphite.950}"
    },
    "surface": {
      "$type": "color",
      "$value": "{color.klaxon.950}"
    },
    "raised": {
      "$type": "color",
      "$value": "{color.klaxon.900}"
    }
  },
  "border": {
    "subtle": {
      "$type": "color",
      "$value": "{color.klaxon.900}"
    },
    "strong": {
      "$type": "color",
      "$value": "{color.klaxon.800}"
    },
    "input": {
      "$type": "color",
      "$value": "{color.graphite.500}"
    }
  },
  "text": {
    "emphasis": {
      "$type": "color",
      "$value": "{color.graphite.100}"
    },
    "primary": {
      "$type": "color",
      "$value": "{color.graphite.150}"
    },
    "secondary": {
      "$type": "color",
      "$value": "{color.graphite.300}"
    },
    "muted": {
      "$type": "color",
      "$value": "{color.graphite.400}"
    },
    "disabled": {
      "$type": "color",
      "$value": "{color.graphite.600}"
    }
  },
  "accent": {
    "default": {
      "$type": "color",
      "$value": "{color.klaxon.200}"
    },
    "hover": {
      "$type": "color",
      "$value": "{color.klaxon.100}"
    },
    "subtle-bg": {
      "$type": "color",
      "$value": "{color.klaxon.900}"
    },
    "on-accent": {
      "$type": "color",
      "$value": "{color.graphite.950}"
    },
    "focus-ring": {
      "$type": "color",
      "$value": "{color.klaxon.200}"
    }
  },
  "status": {
    "success-bg": {
      "$type": "color",
      "$value": "{color.pulse.900}"
    },
    "success-text": {
      "$type": "color",
      "$value": "{color.pulse.100}"
    },
    "warning-bg": {
      "$type": "color",
      "$value": "{color.flare.900}"
    },
    "warning-text": {
      "$type": "color",
      "$value": "{color.flare.100}"
    },
    "danger-bg": {
      "$type": "color",
      "$value": "{color.klaxon.900}"
    },
    "danger-text": {
      "$type": "color",
      "$value": "{color.klaxon.100}"
    }
  },
  "$description": "Redline — Soot chassis, klaxon signal — running hot on purpose. (dark)"
}
